currenttime_mcp/__init__.py
currenttime_mcp/server.py
currenttime_mcp-1.0.1.dist-info/licenses/LICENSE
currenttime_mcp-1.0.1.dist-info/METADATA
currenttime_mcp-1.0.1.dist-info/WHEEL
currenttime_mcp-1.0.1.dist-info/entry_points.txt
currenttime_mcp-1.0.1.dist-info/top_level.txt
currenttime_mcp-1.0.1.dist-info/RECORD
