Metadata-Version: 2.4
Name: currenttime-mcp
Version: 1.0.1
Summary: MCP server for accurate current time with IP-based timezone detection
Author-email: CurrentTime MCP <currenttime-mcp@example.com>
License: MIT License
Project-URL: Homepage, https://github.com/currenttime-mcp/currenttime-mcp
Project-URL: Repository, https://github.com/currenttime-mcp/currenttime-mcp.git
Project-URL: Issues, https://github.com/currenttime-mcp/currenttime-mcp/issues
Keywords: mcp,time,timezone,model-context-protocol,claude
Classifier: Development Status :: 4 - Beta
Classifier: Intended Audience :: Developers
Classifier: Topic :: Software Development :: Libraries :: Python Modules
Classifier: Programming Language :: Python :: 3
Classifier: Programming Language :: Python :: 3.8
Classifier: Programming Language :: Python :: 3.9
Classifier: Programming Language :: Python :: 3.10
Classifier: Programming Language :: Python :: 3.11
Classifier: Programming Language :: Python :: 3.12
Classifier: Programming Language :: Python :: 3.13
Requires-Python: >=3.8
License-File: LICENSE
Requires-Dist: mcp>=1.0.0
Requires-Dist: requests>=2.31.0
Requires-Dist: pytz>=2024.1
Dynamic: license-file
